appmar2/__init__.py
appmar2/__main__.py
appmar2/appmar2.py
appmar2/appmar2.ui
appmar2/ceman.png
appmar2/libappmar2.py
appmar2/libplot.py
appmar2/libstats.py
appmar2-2.0.3.dist-info/LICENSE.txt
appmar2-2.0.3.dist-info/METADATA
appmar2-2.0.3.dist-info/WHEEL
appmar2-2.0.3.dist-info/entry_points.txt
appmar2-2.0.3.dist-info/top_level.txt
appmar2-2.0.3.dist-info/RECORD
