Metadata-Version: 2.1
Name: appmar2
Version: 2.0.3
Summary: Python program for marine climate analysis.
Home-page: https://github.com/cemanetwork/appmar2
Author: CEMAN
License: UNKNOWN
Keywords: marine climate
Platform: UNKNOWN
Classifier: License :: OSI Approved :: MIT License
Requires-Python: >=3.7
Requires-Dist: pygubu (>=0.10.1)
Requires-Dist: pandas (>=1.0.3)
Requires-Dist: numpy (>=1.18.1)
Requires-Dist: xarray (>=0.15.1)
Requires-Dist: scipy (>=1.3.2)
Requires-Dist: matplotlib (>=3.1.3)
Requires-Dist: seaborn (>=0.10.0)
Requires-Dist: statsmodels (>=0.11.0)
Requires-Dist: Cartopy (>=0.17.0)
